kvk_connect/__init__.py
kvk_connect/api/__init__.py
kvk_connect/api/client.py
kvk_connect/api/endpoints.py
kvk_connect/api/session.py
kvk_connect/cli/main.py
kvk_connect/db/__init__.py
kvk_connect/db/basisprofiel_reader.py
kvk_connect/db/basisprofiel_writer.py
kvk_connect/db/init.py
kvk_connect/db/kvkvestigingen_reader.py
kvk_connect/db/kvkvestigingen_writer.py
kvk_connect/db/signaal_reader.py
kvk_connect/db/signaal_writer.py
kvk_connect/db/vestigingenprofiel_reader.py
kvk_connect/db/vestigingsprofiel_writer.py
kvk_connect/logging_config.py
kvk_connect/mappers/__init__.py
kvk_connect/mappers/kvk_record_mapper.py
kvk_connect/mappers/map_mutatie_abonnement_api_to_mutatieabonnement.py
kvk_connect/mappers/map_vestigingen_api_to_vestigingsnummers.py
kvk_connect/mappers/map_vestigingsprofiel_api_to_vestigingsprofiel_domain.py
kvk_connect/models/__init__.py
kvk_connect/models/api/__init__.py
kvk_connect/models/api/abonnementen_api.py
kvk_connect/models/api/basisprofiel_api.py
kvk_connect/models/api/mutatie_abonnementen_api.py
kvk_connect/models/api/mutatiesignalen_api.py
kvk_connect/models/api/vestigingen_api.py
kvk_connect/models/api/vestigingsprofiel_api.py
kvk_connect/models/domain/__init__.py
kvk_connect/models/domain/basisprofiel.py
kvk_connect/models/domain/kvkvestigingsnummersdomain.py
kvk_connect/models/domain/mutatie_abonnement.py
kvk_connect/models/domain/vestigingsadresdomain.py
kvk_connect/models/domain/vestigingsadressendomain.py
kvk_connect/models/domain/vestigingsprofiel_domain.py
kvk_connect/models/orm/base.py
kvk_connect/models/orm/basisprofiel_orm.py
kvk_connect/models/orm/signaal_orm.py
kvk_connect/models/orm/vestigingen_orm.py
kvk_connect/models/orm/vestigingsprofiel_orm.py
kvk_connect/services/__init__.py
kvk_connect/services/record_service.py
kvk_connect/utils/__init__.py
kvk_connect/utils/env.py
kvk_connect/utils/formatting.py
kvk_connect/utils/rate_limit.py
kvk_connect/utils/tools.py
kvk_connect-1.1.0.dist-info/WHEEL
kvk_connect-1.1.0.dist-info/METADATA
kvk_connect-1.1.0.dist-info/RECORD
