Metadata-Version: 2.4
Name: kvk-connect
Version: 1.1.0
Summary: Client + domain mapping for KVK API
Author: Rob Verkuijlen
License-Expression: EUPL-1.2
Classifier: Development Status :: 3 - Alpha
Classifier: Environment :: Web Environment
Classifier: Intended Audience :: Developers
Classifier: License :: OSI Approved :: European Union Public Licence 1.2 (EUPL 1.2)
Classifier: Natural Language :: Dutch
Classifier: Operating System :: OS Independent
Classifier: Programming Language :: Python :: 3.13
Classifier: Topic :: Office/Business
Classifier: Topic :: Software Development :: Libraries
Classifier: Topic :: Software Development :: Libraries :: Python Modules
Classifier: Typing :: Typed
Requires-Dist: requests>=2.32.5
Requires-Dist: python-dotenv>=1.2.1
Requires-Dist: ratelimit>=2.2.1
Requires-Dist: certifi>=2025.10.5
Requires-Dist: sqlalchemy>=2.0.44
Requires-Dist: pyodbc>=5.3.0
Requires-Dist: psycopg2-binary>=2.9.9
Requires-Python: >=3.13
